membar/__init__.py
membar/__init__.pyi
membar/_membar.cp311-win_amd64.pyd
membar/py.typed
pymembar-0.0.4.dist-info/licenses/LICENSE.txt
pymembar-0.0.4.dist-info/METADATA
pymembar-0.0.4.dist-info/WHEEL
pymembar-0.0.4.dist-info/top_level.txt
pymembar-0.0.4.dist-info/RECORD
