Metadata-Version: 2.4
Name: pymembar
Version: 0.0.4
Summary: Memory barrier utilities for Python - provides wmb, rmb, and fence operations
Author-email: fwkrumm <fwkrumm@github.com>
Maintainer-email: fwkrumm <fwkrumm@github.com>
Project-URL: Homepage, https://github.com/fwkrumm/pymembar
Project-URL: Repository, https://github.com/fwkrumm/pymembar
Project-URL: Issues, https://github.com/fwkrumm/pymembar/issues
Project-URL: Documentation, https://github.com/fwkrumm/pymembar/blob/master/README.md
Keywords: memory-barriers,concurrency,low-level,synchronization,threading
Classifier: Development Status :: 4 - Beta
Classifier: Intended Audience :: Developers
Classifier: Operating System :: Microsoft :: Windows
Classifier: Operating System :: POSIX :: Linux
Classifier: Operating System :: MacOS
Classifier: Programming Language :: Python :: 3
Classifier: Programming Language :: Python :: 3.8
Classifier: Programming Language :: Python :: 3.9
Classifier: Programming Language :: Python :: 3.10
Classifier: Programming Language :: Python :: 3.11
Classifier: Programming Language :: Python :: 3.12
Classifier: Programming Language :: Python :: 3.13
Classifier: Programming Language :: C
Classifier: Topic :: Software Development :: Libraries :: Python Modules
Classifier: Topic :: System :: Hardware
Classifier: Topic :: System :: Operating System
Classifier: Typing :: Typed
Requires-Python: >=3.8
License-File: LICENSE.txt
Dynamic: license-file
